SPEEM-1.0.5.dist-info/METADATA
SPEEM-1.0.5.dist-info/RECORD
SPEEM-1.0.5.dist-info/WHEEL
SPEEM-1.0.5.dist-info/entry_points.txt
SPEEM-1.0.5.dist-info/top_level.txt
SPEEM-1.0.5.dist-info/zip-safe
utils/__init__.py
utils/utils.py
