Metadata-Version: 2.1
Name: SPEEM
Version: 1.0.5
Summary: Calculate indicators saved as Excel.
Home-page: https://github.com/haoxiangsnr/Speech_Enhancement_Evaluation_Metrics.git
Author: haoxiang
Author-email: haoxiangsnr@gmail.com
Maintainer: haoxiang
Maintainer-email: haoxiangsnr@gmail.com
License: MIT
Platform: all
Classifier: Development Status :: 4 - Beta
Classifier: Operating System :: OS Independent
Classifier: Intended Audience :: Developers
Classifier: License :: OSI Approved :: MIT License
Classifier: Programming Language :: Python
Classifier: Programming Language :: Python :: Implementation
Classifier: Programming Language :: Python :: 2
Classifier: Programming Language :: Python :: 2.7
Classifier: Programming Language :: Python :: 3
Classifier: Programming Language :: Python :: 3.4
Classifier: Programming Language :: Python :: 3.5
Classifier: Programming Language :: Python :: 3.6
Classifier: Topic :: Software Development :: Libraries
Requires-Dist: pystoi
Requires-Dist: tqdm
Requires-Dist: librosa
Requires-Dist: tablib
